{
  "2026/01/23": {
    "ForeignInvestors": 6593,
    "InvestmentTrust": -25,
    "Dealers": -87,
    "DailyTotal": 6481
  },
  "2026/01/22": {
    "ForeignInvestors": 1654,
    "InvestmentTrust": 0,
    "Dealers": -77,
    "DailyTotal": 1577
  },
  "2026/01/21": {
    "ForeignInvestors": 2218,
    "InvestmentTrust": 0,
    "Dealers": 50,
    "DailyTotal": 2268
  },
  "2026/01/20": {
    "ForeignInvestors": 2561,
    "InvestmentTrust": 0,
    "Dealers": 159,
    "DailyTotal": 2720
  },
  "2026/01/19": {
    "ForeignInvestors": 233,
    "InvestmentTrust": 20,
    "Dealers": 1,
    "DailyTotal": 254
  },
  "2026/01/16": {
    "ForeignInvestors": 4743,
    "InvestmentTrust": 40,
    "Dealers": 369,
    "DailyTotal": 5152
  },
  "2026/01/15": {
    "ForeignInvestors": -1682,
    "InvestmentTrust": 0,
    "Dealers": -233,
    "DailyTotal": -1915
  },
  "2026/01/14": {
    "ForeignInvestors": 2574,
    "InvestmentTrust": 0,
    "Dealers": 352,
    "DailyTotal": 2926
  },
  "2026/01/13": {
    "ForeignInvestors": -590,
    "InvestmentTrust": 0,
    "Dealers": 58,
    "DailyTotal": -532
  },
  "2026/01/12": {
    "ForeignInvestors": 231,
    "InvestmentTrust": 0,
    "Dealers": 22,
    "DailyTotal": 253
  },
  "2026/01/09": {
    "ForeignInvestors": -73,
    "InvestmentTrust": 50,
    "Dealers": 5,
    "DailyTotal": -18
  },
  "2026/01/08": {
    "ForeignInvestors": -530,
    "InvestmentTrust": 0,
    "Dealers": -3,
    "DailyTotal": -533
  },
  "2026/01/07": {
    "ForeignInvestors": -349,
    "InvestmentTrust": 0,
    "Dealers": -39,
    "DailyTotal": -388
  },
  "2026/01/06": {
    "ForeignInvestors": -464,
    "InvestmentTrust": 0,
    "Dealers": 1,
    "DailyTotal": -463
  },
  "2026/01/05": {
    "ForeignInvestors": -137,
    "InvestmentTrust": 0,
    "Dealers": -29,
    "DailyTotal": -166
  },
  "2026/01/02": {
    "ForeignInvestors": -513,
    "InvestmentTrust": 0,
    "Dealers": 15,
    "DailyTotal": -498
  },
  "2025/12/31": {
    "ForeignInvestors": -170,
    "InvestmentTrust": 0,
    "Dealers": -26,
    "DailyTotal": -196
  },
  "2025/12/30": {
    "ForeignInvestors": 238,
    "InvestmentTrust": 0,
    "Dealers": -62,
    "DailyTotal": 176
  },
  "2025/12/29": {
    "ForeignInvestors": 81,
    "InvestmentTrust": 0,
    "Dealers": -20,
    "DailyTotal": 61
  },
  "2025/12/26": {
    "ForeignInvestors": 643,
    "InvestmentTrust": 0,
    "Dealers": -3,
    "DailyTotal": 640
  },
  "2025/12/24": {
    "ForeignInvestors": 498,
    "InvestmentTrust": 0,
    "Dealers": -18,
    "DailyTotal": 480
  },
  "2025/12/23": {
    "ForeignInvestors": 564,
    "InvestmentTrust": 0,
    "Dealers": -26,
    "DailyTotal": 538
  },
  "2025/12/22": {
    "ForeignInvestors": 809,
    "InvestmentTrust": 0,
    "Dealers": 80,
    "DailyTotal": 889
  },
  "2025/12/19": {
    "ForeignInvestors": 794,
    "InvestmentTrust": 0,
    "Dealers": 29,
    "DailyTotal": 823
  },
  "2025/12/18": {
    "ForeignInvestors": -446,
    "InvestmentTrust": 0,
    "Dealers": -23,
    "DailyTotal": -469
  },
  "2025/12/17": {
    "ForeignInvestors": -225,
    "InvestmentTrust": 0,
    "Dealers": -26,
    "DailyTotal": -251
  },
  "2025/12/16": {
    "ForeignInvestors": -575,
    "InvestmentTrust": 0,
    "Dealers": -121,
    "DailyTotal": -696
  },
  "2025/12/15": {
    "ForeignInvestors": -1587,
    "InvestmentTrust": 0,
    "Dealers": 128,
    "DailyTotal": -1459
  },
  "2025/12/12": {
    "ForeignInvestors": 1303,
    "InvestmentTrust": 0,
    "Dealers": 120,
    "DailyTotal": 1423
  },
  "2025/12/11": {
    "ForeignInvestors": -17,
    "InvestmentTrust": 0,
    "Dealers": 0,
    "DailyTotal": -17
  },
  "2025/12/10": {
    "ForeignInvestors": 14,
    "InvestmentTrust": 0,
    "Dealers": 4,
    "DailyTotal": 18
  },
  "2025/12/09": {
    "ForeignInvestors": -190,
    "InvestmentTrust": 0,
    "Dealers": 3,
    "DailyTotal": -187
  },
  "2025/12/08": {
    "ForeignInvestors": 108,
    "InvestmentTrust": 0,
    "Dealers": 31,
    "DailyTotal": 139
  },
  "2025/12/05": {
    "ForeignInvestors": -35,
    "InvestmentTrust": 0,
    "Dealers": 5,
    "DailyTotal": -30
  },
  "2025/12/04": {
    "ForeignInvestors": 249,
    "InvestmentTrust": 0,
    "Dealers": 2,
    "DailyTotal": 251
  },
  "2025/12/03": {
    "ForeignInvestors": 120,
    "InvestmentTrust": 0,
    "Dealers": -7,
    "DailyTotal": 113
  },
  "2025/12/02": {
    "ForeignInvestors": -137,
    "InvestmentTrust": -45,
    "Dealers": 1,
    "DailyTotal": -181
  }
}