{
  "2026/01/23": {
    "ForeignInvestors": 3707,
    "InvestmentTrust": 4097,
    "Dealers": 445,
    "DailyTotal": 8249
  },
  "2026/01/22": {
    "ForeignInvestors": -259,
    "InvestmentTrust": 1744,
    "Dealers": 726,
    "DailyTotal": 2211
  },
  "2026/01/21": {
    "ForeignInvestors": 496,
    "InvestmentTrust": -468,
    "Dealers": -1027,
    "DailyTotal": -999
  },
  "2026/01/20": {
    "ForeignInvestors": 10274,
    "InvestmentTrust": 2046,
    "Dealers": -1396,
    "DailyTotal": 10924
  },
  "2026/01/19": {
    "ForeignInvestors": -4128,
    "InvestmentTrust": 615,
    "Dealers": -1081,
    "DailyTotal": -4594
  },
  "2026/01/16": {
    "ForeignInvestors": -1320,
    "InvestmentTrust": 1007,
    "Dealers": -791,
    "DailyTotal": -1104
  },
  "2026/01/15": {
    "ForeignInvestors": -5210,
    "InvestmentTrust": 10145,
    "Dealers": 268,
    "DailyTotal": 5203
  },
  "2026/01/14": {
    "ForeignInvestors": -18566,
    "InvestmentTrust": 1379,
    "Dealers": -600,
    "DailyTotal": -17787
  },
  "2026/01/13": {
    "ForeignInvestors": -4204,
    "InvestmentTrust": 8486,
    "Dealers": -1731,
    "DailyTotal": 2551
  },
  "2026/01/12": {
    "ForeignInvestors": 5565,
    "InvestmentTrust": 1660,
    "Dealers": -1492,
    "DailyTotal": 5733
  },
  "2026/01/09": {
    "ForeignInvestors": 9422,
    "InvestmentTrust": 167,
    "Dealers": 1066,
    "DailyTotal": 10655
  },
  "2026/01/08": {
    "ForeignInvestors": -4001,
    "InvestmentTrust": 509,
    "Dealers": -2309,
    "DailyTotal": -5801
  },
  "2026/01/07": {
    "ForeignInvestors": 4532,
    "InvestmentTrust": 3873,
    "Dealers": 355,
    "DailyTotal": 8760
  },
  "2026/01/06": {
    "ForeignInvestors": 19369,
    "InvestmentTrust": 233,
    "Dealers": 281,
    "DailyTotal": 19883
  },
  "2026/01/05": {
    "ForeignInvestors": 463,
    "InvestmentTrust": -2143,
    "Dealers": -289,
    "DailyTotal": -1969
  },
  "2026/01/02": {
    "ForeignInvestors": -1465,
    "InvestmentTrust": 156,
    "Dealers": 276,
    "DailyTotal": -1033
  },
  "2025/12/31": {
    "ForeignInvestors": -5808,
    "InvestmentTrust": -70,
    "Dealers": -2028,
    "DailyTotal": -7906
  },
  "2025/12/30": {
    "ForeignInvestors": -1498,
    "InvestmentTrust": -1075,
    "Dealers": 198,
    "DailyTotal": -2375
  },
  "2025/12/29": {
    "ForeignInvestors": -8572,
    "InvestmentTrust": -747,
    "Dealers": -458,
    "DailyTotal": -9777
  },
  "2025/12/26": {
    "ForeignInvestors": -9511,
    "InvestmentTrust": -1530,
    "Dealers": 335,
    "DailyTotal": -10706
  },
  "2025/12/24": {
    "ForeignInvestors": -13836,
    "InvestmentTrust": -9,
    "Dealers": -85,
    "DailyTotal": -13930
  },
  "2025/12/23": {
    "ForeignInvestors": 10213,
    "InvestmentTrust": 118,
    "Dealers": 1163,
    "DailyTotal": 11494
  },
  "2025/12/22": {
    "ForeignInvestors": 16336,
    "InvestmentTrust": 115,
    "Dealers": 3139,
    "DailyTotal": 19590
  },
  "2025/12/19": {
    "ForeignInvestors": -12702,
    "InvestmentTrust": 744,
    "Dealers": 62,
    "DailyTotal": -11896
  },
  "2025/12/18": {
    "ForeignInvestors": -16828,
    "InvestmentTrust": 134,
    "Dealers": 2019,
    "DailyTotal": -14675
  },
  "2025/12/17": {
    "ForeignInvestors": 4122,
    "InvestmentTrust": 4000,
    "Dealers": 2014,
    "DailyTotal": 10136
  },
  "2025/12/16": {
    "ForeignInvestors": -10834,
    "InvestmentTrust": 3461,
    "Dealers": -685,
    "DailyTotal": -8058
  },
  "2025/12/15": {
    "ForeignInvestors": 85,
    "InvestmentTrust": 72,
    "Dealers": 5567,
    "DailyTotal": 5724
  },
  "2025/12/12": {
    "ForeignInvestors": -370,
    "InvestmentTrust": 1154,
    "Dealers": 1177,
    "DailyTotal": 1961
  },
  "2025/12/11": {
    "ForeignInvestors": 1041,
    "InvestmentTrust": 15,
    "Dealers": -26,
    "DailyTotal": 1030
  },
  "2025/12/10": {
    "ForeignInvestors": 141,
    "InvestmentTrust": -80,
    "Dealers": -469,
    "DailyTotal": -408
  },
  "2025/12/09": {
    "ForeignInvestors": 2555,
    "InvestmentTrust": -427,
    "Dealers": 74,
    "DailyTotal": 2202
  },
  "2025/12/08": {
    "ForeignInvestors": -473,
    "InvestmentTrust": -82,
    "Dealers": 459,
    "DailyTotal": -96
  },
  "2025/12/05": {
    "ForeignInvestors": 800,
    "InvestmentTrust": -440,
    "Dealers": -30,
    "DailyTotal": 330
  },
  "2025/12/04": {
    "ForeignInvestors": -400,
    "InvestmentTrust": 6,
    "Dealers": 145,
    "DailyTotal": -249
  },
  "2025/12/03": {
    "ForeignInvestors": -2913,
    "InvestmentTrust": 77,
    "Dealers": 151,
    "DailyTotal": -2685
  },
  "2025/12/02": {
    "ForeignInvestors": 3485,
    "InvestmentTrust": 14,
    "Dealers": 928,
    "DailyTotal": 4427
  }
}