{
  "2026/02/03": {
    "sma5": 21.97,
    "sma20": 21.91,
    "sma60": 21.85,
    "sma120": 21.85,
    "sma240": 22.24
  },
  "2026/02/02": {
    "sma5": 22.01,
    "sma20": 21.91,
    "sma60": 21.85,
    "sma120": 21.85,
    "sma240": 22.24
  },
  "2026/01/30": {
    "sma5": 22.01,
    "sma20": 21.91,
    "sma60": 21.85,
    "sma120": 21.85,
    "sma240": 22.25
  },
  "2026/01/29": {
    "sma5": 22.01,
    "sma20": 21.9,
    "sma60": 21.86,
    "sma120": 21.85,
    "sma240": 22.25
  },
  "2026/01/28": {
    "sma5": 21.97,
    "sma20": 21.89,
    "sma60": 21.85,
    "sma120": 21.84,
    "sma240": 22.26
  },
  "2026/01/27": {
    "sma5": 21.91,
    "sma20": 21.86,
    "sma60": 21.85,
    "sma120": 21.84,
    "sma240": 22.26
  },
  "2026/01/26": {
    "sma5": 21.88,
    "sma20": 21.85,
    "sma60": 21.84,
    "sma120": 21.84,
    "sma240": 22.27
  },
  "2026/01/23": {
    "sma5": 21.89,
    "sma20": 21.85,
    "sma60": 21.85,
    "sma120": 21.83,
    "sma240": 22.27
  },
  "2026/01/22": {
    "sma5": 21.9,
    "sma20": 21.84,
    "sma60": 21.84,
    "sma120": 21.83,
    "sma240": 22.28
  },
  "2026/01/21": {
    "sma5": 21.9,
    "sma20": 21.83,
    "sma60": 21.84,
    "sma120": 21.83,
    "sma240": 22.28
  },
  "2026/01/20": {
    "sma5": 21.9,
    "sma20": 21.82,
    "sma60": 21.84,
    "sma120": 21.83,
    "sma240": 22.29
  },
  "2026/01/19": {
    "sma5": 21.89,
    "sma20": 21.81,
    "sma60": 21.84,
    "sma120": 21.83,
    "sma240": 22.29
  },
  "2026/01/16": {
    "sma5": 21.87,
    "sma20": 21.8,
    "sma60": 21.84,
    "sma120": 21.83,
    "sma240": 22.3
  },
  "2026/01/15": {
    "sma5": 21.86,
    "sma20": 21.79,
    "sma60": 21.84,
    "sma120": 21.82,
    "sma240": 22.3
  },
  "2026/01/14": {
    "sma5": 21.86,
    "sma20": 21.78,
    "sma60": 21.84,
    "sma120": 21.82,
    "sma240": 22.31
  },
  "2026/01/13": {
    "sma5": 21.86,
    "sma20": 21.78,
    "sma60": 21.84,
    "sma120": 21.82,
    "sma240": 22.31
  },
  "2026/01/12": {
    "sma5": 21.85,
    "sma20": 21.78,
    "sma60": 21.84,
    "sma120": 21.82,
    "sma240": 22.31
  },
  "2026/01/09": {
    "sma5": 21.85,
    "sma20": 21.78,
    "sma60": 21.84,
    "sma120": 21.82,
    "sma240": 22.32
  },
  "2026/01/08": {
    "sma5": 21.83,
    "sma20": 21.78,
    "sma60": 21.84,
    "sma120": 21.81,
    "sma240": 22.32
  },
  "2026/01/07": {
    "sma5": 21.81,
    "sma20": 21.78,
    "sma60": 21.84,
    "sma120": 21.81,
    "sma240": 22.32
  },
  "2026/01/06": {
    "sma5": 21.78,
    "sma20": 21.78,
    "sma60": 21.84,
    "sma120": 21.81,
    "sma240": 22.32
  },
  "2026/01/05": {
    "sma5": 21.77,
    "sma20": 21.78,
    "sma60": 21.84,
    "sma120": 21.81,
    "sma240": 22.33
  },
  "2026/01/02": {
    "sma5": 21.77,
    "sma20": 21.79,
    "sma60": 21.84,
    "sma120": 21.81,
    "sma240": 22.33
  },
  "2025/12/31": {
    "sma5": 21.75,
    "sma20": 21.8,
    "sma60": 21.84,
    "sma120": 21.81,
    "sma240": 22.34
  },
  "2025/12/30": {
    "sma5": 21.74,
    "sma20": 21.8,
    "sma60": 21.85,
    "sma120": 21.81,
    "sma240": 22.34
  },
  "2025/12/29": {
    "sma5": 21.74,
    "sma20": 21.8,
    "sma60": 21.85,
    "sma120": 21.81,
    "sma240": 22.35
  },
  "2025/12/26": {
    "sma5": 21.74,
    "sma20": 21.8,
    "sma60": 21.85,
    "sma120": 21.81,
    "sma240": 22.35
  },
  "2025/12/24": {
    "sma5": 21.72,
    "sma20": 21.8,
    "sma60": 21.85,
    "sma120": 21.81,
    "sma240": 22.36
  },
  "2025/12/23": {
    "sma5": 21.72,
    "sma20": 21.81,
    "sma60": 21.85,
    "sma120": 21.81,
    "sma240": 22.36
  },
  "2025/12/22": {
    "sma5": 21.72,
    "sma20": 21.82,
    "sma60": 21.85,
    "sma120": 21.82,
    "sma240": 22.37
  },
  "2025/12/19": {
    "sma5": 21.73,
    "sma20": 21.82,
    "sma60": 21.85,
    "sma120": 21.82,
    "sma240": 22.37
  },
  "2025/12/18": {
    "sma5": 21.75,
    "sma20": 21.82,
    "sma60": 21.86,
    "sma120": 21.82,
    "sma240": 22.38
  },
  "2025/12/17": {
    "sma5": 21.78,
    "sma20": 21.83,
    "sma60": 21.86,
    "sma120": 21.83,
    "sma240": 22.38
  },
  "2025/12/16": {
    "sma5": 21.81,
    "sma20": 21.83,
    "sma60": 21.86,
    "sma120": 21.84,
    "sma240": 22.39
  },
  "2025/12/15": {
    "sma5": 21.84,
    "sma20": 21.83,
    "sma60": 21.86,
    "sma120": 21.85,
    "sma240": 22.39
  },
  "2025/12/12": {
    "sma5": 21.86,
    "sma20": 21.83,
    "sma60": 21.86,
    "sma120": 21.86,
    "sma240": 22.39
  },
  "2025/12/11": {
    "sma5": 21.87,
    "sma20": 21.83,
    "sma60": 21.86,
    "sma120": 21.87,
    "sma240": 22.4
  },
  "2025/12/10": {
    "sma5": 21.89,
    "sma20": 21.84,
    "sma60": 21.86,
    "sma120": 21.88,
    "sma240": 22.4
  },
  "2025/12/09": {
    "sma5": 21.9,
    "sma20": 21.85,
    "sma60": 21.86,
    "sma120": 21.89,
    "sma240": 22.41
  },
  "2025/12/08": {
    "sma5": 21.9,
    "sma20": 21.85,
    "sma60": 21.86,
    "sma120": 21.9,
    "sma240": 22.41
  },
  "2025/12/05": {
    "sma5": 21.87,
    "sma20": 21.86,
    "sma60": 21.86,
    "sma120": 21.91,
    "sma240": 22.42
  },
  "2025/12/04": {
    "sma5": 21.84,
    "sma20": 21.86,
    "sma60": 21.86,
    "sma120": 21.92,
    "sma240": 22.42
  },
  "2025/12/03": {
    "sma5": 21.81,
    "sma20": 21.86,
    "sma60": 21.86,
    "sma120": 21.93,
    "sma240": 22.43
  },
  "2025/12/02": {
    "sma5": 21.8,
    "sma20": 21.87,
    "sma60": 21.86,
    "sma120": 21.93,
    "sma240": 22.43
  }
}