{
  "2026/06/08": {
    "price": 41.45,
    "open": 40.9,
    "high": 41.8,
    "low": 40.5,
    "volume": 2543,
    "sma5": 41.91,
    "sma20": 39.53,
    "sma60": 39.91,
    "sma120": 39.23,
    "sma240": 39.98
  },
  "2026/06/05": {
    "price": 43.35,
    "open": 42.95,
    "high": 43.4,
    "low": 42.35,
    "volume": 2247,
    "sma5": 41.58,
    "sma20": 39.46,
    "sma60": 39.88,
    "sma120": 39.21,
    "sma240": 39.98
  },
  "2026/06/04": {
    "price": 43,
    "open": 41.7,
    "high": 43.75,
    "low": 41.45,
    "volume": 2825,
    "sma5": 40.78,
    "sma20": 39.27,
    "sma60": 39.77,
    "sma120": 39.17,
    "sma240": 39.97
  },
  "2026/06/03": {
    "price": 42.1,
    "open": 39.85,
    "high": 42.35,
    "low": 39.5,
    "volume": 4235,
    "sma5": 39.92,
    "sma20": 39.11,
    "sma60": 39.69,
    "sma120": 39.13,
    "sma240": 39.97
  },
  "2026/06/02": {
    "price": 39.65,
    "open": 39.6,
    "high": 39.8,
    "low": 39.3,
    "volume": 927,
    "sma5": 39.27,
    "sma20": 38.97,
    "sma60": 39.64,
    "sma120": 39.11,
    "sma240": 39.97
  },
  "2026/06/01": {
    "price": 39.8,
    "open": 39.3,
    "high": 39.9,
    "low": 38.65,
    "volume": 1191,
    "sma5": 39.11,
    "sma20": 39.03,
    "sma60": 39.61,
    "sma120": 39.1,
    "sma240": 39.99
  },
  "2026/05/29": {
    "price": 39.35,
    "open": 38.6,
    "high": 39.5,
    "low": 38.6,
    "volume": 1183,
    "sma5": 39.07,
    "sma20": 39.07,
    "sma60": 39.56,
    "sma120": 39.1,
    "sma240": 40
  },
  "2026/05/28": {
    "price": 38.7,
    "open": 39.15,
    "high": 39.15,
    "low": 38.4,
    "volume": 859,
    "sma5": 38.85,
    "sma20": 39.14,
    "sma60": 39.55,
    "sma120": 39.09,
    "sma240": 40.01
  },
  "2026/05/27": {
    "price": 38.85,
    "open": 38.95,
    "high": 39.1,
    "low": 38.5,
    "volume": 929,
    "sma5": 38.78,
    "sma20": 39.25,
    "sma60": 39.56,
    "sma120": 39.07,
    "sma240": 40.02
  },
  "2026/05/26": {
    "price": 38.85,
    "open": 39.9,
    "high": 40.15,
    "low": 38.75,
    "volume": 1847,
    "sma5": 38.67,
    "sma20": 39.3,
    "sma60": 39.56,
    "sma120": 39.05,
    "sma240": 40.03
  },
  "2026/05/25": {
    "price": 39.6,
    "open": 38.5,
    "high": 39.9,
    "low": 38.4,
    "volume": 1718,
    "sma5": 38.54,
    "sma20": 39.29,
    "sma60": 39.58,
    "sma120": 39.03,
    "sma240": 40.04
  },
  "2026/05/22": {
    "price": 38.25,
    "open": 38.4,
    "high": 38.5,
    "low": 38.2,
    "volume": 910,
    "sma5": 38.23,
    "sma20": 39.25,
    "sma60": 39.58,
    "sma120": 39,
    "sma240": 40.05
  },
  "2026/05/21": {
    "price": 38.35,
    "open": 38.2,
    "high": 38.55,
    "low": 38.2,
    "volume": 941,
    "sma5": 38.26,
    "sma20": 39.27,
    "sma60": 39.6,
    "sma120": 38.99,
    "sma240": 40.07
  },
  "2026/05/20": {
    "price": 38.3,
    "open": 38.25,
    "high": 38.5,
    "low": 38,
    "volume": 809,
    "sma5": 38.32,
    "sma20": 39.33,
    "sma60": 39.63,
    "sma120": 38.98,
    "sma240": 40.09
  },
  "2026/05/19": {
    "price": 38.2,
    "open": 38,
    "high": 38.5,
    "low": 38,
    "volume": 526,
    "sma5": 38.37,
    "sma20": 39.42,
    "sma60": 39.65,
    "sma120": 38.97,
    "sma240": 40.11
  },
  "2026/05/18": {
    "price": 38.05,
    "open": 38.4,
    "high": 38.4,
    "low": 38,
    "volume": 997,
    "sma5": 38.57,
    "sma20": 39.53,
    "sma60": 39.67,
    "sma120": 38.97,
    "sma240": 40.13
  },
  "2026/05/15": {
    "price": 38.4,
    "open": 38.75,
    "high": 38.95,
    "low": 38.25,
    "volume": 764,
    "sma5": 38.94,
    "sma20": 39.68,
    "sma60": 39.68,
    "sma120": 38.97,
    "sma240": 40.16
  },
  "2026/05/14": {
    "price": 38.65,
    "open": 38.55,
    "high": 39.15,
    "low": 38.45,
    "volume": 554,
    "sma5": 39.19,
    "sma20": 39.81,
    "sma60": 39.69,
    "sma120": 38.97,
    "sma240": 40.18
  },
  "2026/05/13": {
    "price": 38.55,
    "open": 39,
    "high": 39,
    "low": 38.4,
    "volume": 1030,
    "sma5": 39.41,
    "sma20": 39.91,
    "sma60": 39.71,
    "sma120": 38.97,
    "sma240": 40.2
  },
  "2026/05/12": {
    "price": 39.2,
    "open": 39.95,
    "high": 39.95,
    "low": 39.1,
    "volume": 810,
    "sma5": 39.58,
    "sma20": 40.05,
    "sma60": 39.72,
    "sma120": 38.97,
    "sma240": 40.22
  },
  "2026/05/11": {
    "price": 39.9,
    "open": 39.75,
    "high": 40.45,
    "low": 39.6,
    "volume": 884,
    "sma5": 39.89,
    "sma20": 40.15,
    "sma60": 39.71,
    "sma120": 38.97,
    "sma240": 40.24
  },
  "2026/05/08": {
    "price": 39.65,
    "open": 39.85,
    "high": 39.85,
    "low": 39.05,
    "volume": 681,
    "sma5": 40.05,
    "sma20": 40.2,
    "sma60": 39.7,
    "sma120": 38.96,
    "sma240": 40.26
  },
  "2026/05/07": {
    "price": 39.75,
    "open": 39.45,
    "high": 39.8,
    "low": 39.1,
    "volume": 774,
    "sma5": 40.25,
    "sma20": 40.26,
    "sma60": 39.71,
    "sma120": 38.95,
    "sma240": 40.27
  },
  "2026/05/06": {
    "price": 39.4,
    "open": 40.45,
    "high": 40.45,
    "low": 39.25,
    "volume": 2553,
    "sma5": 40.47,
    "sma20": 40.34,
    "sma60": 39.69,
    "sma120": 38.95,
    "sma240": 40.28
  },
  "2026/05/05": {
    "price": 40.75,
    "open": 40.9,
    "high": 41.2,
    "low": 40.45,
    "volume": 1153,
    "sma5": 40.59,
    "sma20": 40.4,
    "sma60": 39.68,
    "sma120": 38.95,
    "sma240": 40.29
  },
  "2026/05/04": {
    "price": 40.7,
    "open": 40.65,
    "high": 40.95,
    "low": 40.45,
    "volume": 1016,
    "sma5": 40.15,
    "sma20": 40.37,
    "sma60": 39.66,
    "sma120": 38.94,
    "sma240": 40.29
  },
  "2026/04/30": {
    "price": 40.65,
    "open": 40.85,
    "high": 40.9,
    "low": 40.45,
    "volume": 872,
    "sma5": 39.78,
    "sma20": 40.33,
    "sma60": 39.62,
    "sma120": 38.94,
    "sma240": 40.29
  },
  "2026/04/29": {
    "price": 40.85,
    "open": 40.2,
    "high": 40.9,
    "low": 40.1,
    "volume": 1046,
    "sma5": 39.37,
    "sma20": 40.28,
    "sma60": 39.58,
    "sma120": 38.93,
    "sma240": 40.31
  },
  "2026/04/28": {
    "price": 40,
    "open": 38.9,
    "high": 40,
    "low": 38.9,
    "volume": 1183,
    "sma5": 39.13,
    "sma20": 40.23,
    "sma60": 39.53,
    "sma120": 38.93,
    "sma240": 40.32
  },
  "2026/04/27": {
    "price": 38.55,
    "open": 38.85,
    "high": 38.85,
    "low": 38.2,
    "volume": 772,
    "sma5": 39.13,
    "sma20": 40.23,
    "sma60": 39.51,
    "sma120": 38.94,
    "sma240": 40.34
  },
  "2026/04/24": {
    "price": 38.85,
    "open": 38.85,
    "high": 39,
    "low": 38.5,
    "volume": 518,
    "sma5": 39.52,
    "sma20": 40.32,
    "sma60": 39.52,
    "sma120": 38.95,
    "sma240": 40.36
  },
  "2026/04/23": {
    "price": 38.6,
    "open": 39.6,
    "high": 39.65,
    "low": 38.25,
    "volume": 1336,
    "sma5": 39.95,
    "sma20": 40.38,
    "sma60": 39.52,
    "sma120": 38.97,
    "sma240": 40.38
  },
  "2026/04/22": {
    "price": 39.65,
    "open": 40,
    "high": 40.1,
    "low": 39.6,
    "volume": 849,
    "sma5": 40.43,
    "sma20": 40.46,
    "sma60": 39.54,
    "sma120": 38.99,
    "sma240": 40.4
  },
  "2026/04/21": {
    "price": 40,
    "open": 40.5,
    "high": 40.5,
    "low": 40,
    "volume": 872,
    "sma5": 40.64,
    "sma20": 40.51,
    "sma60": 39.52,
    "sma120": 39,
    "sma240": 40.42
  },
  "2026/04/20": {
    "price": 40.5,
    "open": 41,
    "high": 41.15,
    "low": 40.3,
    "volume": 707,
    "sma5": 40.88,
    "sma20": 40.52,
    "sma60": 39.5,
    "sma120": 39,
    "sma240": 40.43
  },
  "2026/04/17": {
    "price": 41,
    "open": 41.2,
    "high": 41.35,
    "low": 40.9,
    "volume": 568,
    "sma5": 41.03,
    "sma20": 40.48,
    "sma60": 39.48,
    "sma120": 39,
    "sma240": 40.44
  },
  "2026/04/16": {
    "price": 41,
    "open": 40.9,
    "high": 41.1,
    "low": 40.8,
    "volume": 728,
    "sma5": 41,
    "sma20": 40.43,
    "sma60": 39.44,
    "sma120": 38.99,
    "sma240": 40.45
  },
  "2026/04/15": {
    "price": 40.7,
    "open": 41.3,
    "high": 41.3,
    "low": 40.7,
    "volume": 616,
    "sma5": 41,
    "sma20": 40.37,
    "sma60": 39.4,
    "sma120": 38.98,
    "sma240": 40.45
  },
  "2026/04/14": {
    "price": 41.2,
    "open": 41.2,
    "high": 41.45,
    "low": 41,
    "volume": 717,
    "sma5": 41.11,
    "sma20": 40.29,
    "sma60": 39.39,
    "sma120": 38.98,
    "sma240": 40.47
  },
  "2026/04/13": {
    "price": 41.25,
    "open": 41.1,
    "high": 41.25,
    "low": 40.75,
    "volume": 677,
    "sma5": 41,
    "sma20": 40.18,
    "sma60": 39.33,
    "sma120": 38.98,
    "sma240": 40.48
  },
  "2026/04/10": {
    "price": 40.85,
    "open": 41.5,
    "high": 41.55,
    "low": 40.75,
    "volume": 723,
    "sma5": 40.77,
    "sma20": 40.06,
    "sma60": 39.28,
    "sma120": 38.98,
    "sma240": 40.49
  },
  "2026/04/09": {
    "price": 41,
    "open": 41.25,
    "high": 41.25,
    "low": 40.7,
    "volume": 578,
    "sma5": 40.58,
    "sma20": 39.98,
    "sma60": 39.22,
    "sma120": 38.98,
    "sma240": 40.5
  },
  "2026/04/08": {
    "price": 41.25,
    "open": 40.85,
    "high": 41.35,
    "low": 40.55,
    "volume": 1759,
    "sma5": 40.3,
    "sma20": 39.79,
    "sma60": 39.17,
    "sma120": 38.98,
    "sma240": 40.51
  },
  "2026/04/07": {
    "price": 40.65,
    "open": 40.15,
    "high": 40.75,
    "low": 40.1,
    "volume": 833,
    "sma5": 40.02,
    "sma20": 39.62,
    "sma60": 39.12,
    "sma120": 38.99,
    "sma240": 40.51
  },
  "2026/04/02": {
    "price": 40.1,
    "open": 40.3,
    "high": 40.3,
    "low": 39.9,
    "volume": 433,
    "sma5": 39.9,
    "sma20": 39.54,
    "sma60": 39.08,
    "sma120": 39,
    "sma240": 40.51
  },
  "2026/04/01": {
    "price": 39.9,
    "open": 40,
    "high": 40.2,
    "low": 39.55,
    "volume": 460,
    "sma5": 39.96,
    "sma20": 39.43,
    "sma60": 39.04,
    "sma120": 39.02,
    "sma240": 40.5
  },
  "2026/03/31": {
    "price": 39.6,
    "open": 39.7,
    "high": 40.6,
    "low": 39.4,
    "volume": 862,
    "sma5": 39.98,
    "sma20": 39.29,
    "sma60": 39,
    "sma120": 39.04,
    "sma240": 40.5
  },
  "2026/03/30": {
    "price": 39.85,
    "open": 40.25,
    "high": 40.8,
    "low": 39.8,
    "volume": 723,
    "sma5": 40.11,
    "sma20": 39.24,
    "sma60": 38.97,
    "sma120": 39.07,
    "sma240": 40.52
  },
  "2026/03/27": {
    "price": 40.05,
    "open": 40.3,
    "high": 40.55,
    "low": 39.65,
    "volume": 806,
    "sma5": 40.27,
    "sma20": 39.2,
    "sma60": 38.94,
    "sma120": 39.09,
    "sma240": 40.55
  },
  "2026/03/26": {
    "price": 40.4,
    "open": 40.3,
    "high": 40.85,
    "low": 40.2,
    "volume": 710,
    "sma5": 40.31,
    "sma20": 39.16,
    "sma60": 38.9,
    "sma120": 39.11,
    "sma240": 40.58
  },
  "2026/03/25": {
    "price": 40,
    "open": 40.7,
    "high": 40.7,
    "low": 40,
    "volume": 1718,
    "sma5": 40.14,
    "sma20": 39.14,
    "sma60": 38.84,
    "sma120": 39.13,
    "sma240": 40.61
  },
  "2026/03/24": {
    "price": 40.25,
    "open": 41,
    "high": 41,
    "low": 40.15,
    "volume": 1048,
    "sma5": 40.16,
    "sma20": 39.11,
    "sma60": 38.8,
    "sma120": 39.15,
    "sma240": 40.64
  },
  "2026/03/23": {
    "price": 40.65,
    "open": 40.4,
    "high": 41,
    "low": 40.2,
    "volume": 1592,
    "sma5": 40.05,
    "sma20": 39.08,
    "sma60": 38.76,
    "sma120": 39.17,
    "sma240": 40.68
  },
  "2026/03/20": {
    "price": 40.25,
    "open": 39.95,
    "high": 41.3,
    "low": 39.95,
    "volume": 3060,
    "sma5": 39.74,
    "sma20": 39.04,
    "sma60": 38.71,
    "sma120": 39.18,
    "sma240": 40.72
  },
  "2026/03/19": {
    "price": 39.55,
    "open": 39.9,
    "high": 39.9,
    "low": 39.3,
    "volume": 646,
    "sma5": 39.52,
    "sma20": 39.01,
    "sma60": 38.67,
    "sma120": 39.19,
    "sma240": 40.76
  },
  "2026/03/18": {
    "price": 40.1,
    "open": 40.15,
    "high": 40.5,
    "low": 39.7,
    "volume": 981,
    "sma5": 39.38,
    "sma20": 39.01,
    "sma60": 38.63,
    "sma120": 39.21,
    "sma240": 40.81
  },
  "2026/03/17": {
    "price": 39.7,
    "open": 39.2,
    "high": 39.95,
    "low": 39.2,
    "volume": 731,
    "sma5": 39.19,
    "sma20": 38.94,
    "sma60": 38.59,
    "sma120": 39.22,
    "sma240": 40.86
  },
  "2026/03/16": {
    "price": 39.1,
    "open": 39.15,
    "high": 39.5,
    "low": 39.05,
    "volume": 472,
    "sma5": 38.68,
    "sma20": 38.9,
    "sma60": 38.56,
    "sma120": 39.25,
    "sma240": 40.91
  },
  "2026/03/13": {
    "price": 39.15,
    "open": 38.85,
    "high": 39.25,
    "low": 38.6,
    "volume": 725,
    "sma5": 38.44,
    "sma20": 38.93,
    "sma60": 38.54,
    "sma120": 39.28,
    "sma240": 40.96
  },
  "2026/03/12": {
    "price": 38.85,
    "open": 39,
    "high": 39.2,
    "low": 38.75,
    "volume": 708,
    "sma5": 38.42,
    "sma20": 38.92,
    "sma60": 38.54,
    "sma120": 39.32,
    "sma240": 41.01
  },
  "2026/03/11": {
    "price": 39.15,
    "open": 37.45,
    "high": 39.15,
    "low": 37.45,
    "volume": 1598,
    "sma5": 38.25,
    "sma20": 38.92,
    "sma60": 38.54,
    "sma120": 39.36,
    "sma240": 41.07
  },
  "2026/03/10": {
    "price": 37.15,
    "open": 37.9,
    "high": 38.05,
    "low": 37,
    "volume": 1635,
    "sma5": 37.83,
    "sma20": 38.94,
    "sma60": 38.54,
    "sma120": 39.41,
    "sma240": 41.12
  },
  "2026/03/09": {
    "price": 37.9,
    "open": 37.95,
    "high": 38.6,
    "low": 37.5,
    "volume": 887,
    "sma5": 38.12,
    "sma20": 39.07,
    "sma60": 38.56,
    "sma120": 39.47,
    "sma240": 41.18
  },
  "2026/03/06": {
    "price": 39.05,
    "open": 38.05,
    "high": 39.15,
    "low": 37.9,
    "volume": 912,
    "sma5": 38.34,
    "sma20": 39.13,
    "sma60": 38.58,
    "sma120": 39.52,
    "sma240": 41.24
  },
  "2026/03/05": {
    "price": 38,
    "open": 37.6,
    "high": 38.2,
    "low": 37.45,
    "volume": 717,
    "sma5": 38.38,
    "sma20": 39.1,
    "sma60": 38.58,
    "sma120": 39.56,
    "sma240": 41.31
  },
  "2026/03/04": {
    "price": 37.05,
    "open": 38.5,
    "high": 38.5,
    "low": 37.05,
    "volume": 1750,
    "sma5": 38.78,
    "sma20": 39.17,
    "sma60": 38.59,
    "sma120": 39.61,
    "sma240": 41.37
  },
  "2026/03/03": {
    "price": 38.6,
    "open": 38.75,
    "high": 39.05,
    "low": 38.35,
    "volume": 906,
    "sma5": 39.26,
    "sma20": 39.25,
    "sma60": 38.63,
    "sma120": 39.67,
    "sma240": 41.44
  },
  "2026/03/02": {
    "price": 39,
    "open": 39.1,
    "high": 39.25,
    "low": 38.55,
    "volume": 507,
    "sma5": 39.45,
    "sma20": 39.22,
    "sma60": 38.62,
    "sma120": 39.71,
    "sma240": 41.49
  },
  "2026/02/26": {
    "price": 39.25,
    "open": 40.15,
    "high": 40.15,
    "low": 39.2,
    "volume": 823,
    "sma5": 39.65,
    "sma20": 39.17,
    "sma60": 38.59,
    "sma120": 39.75,
    "sma240": 41.55
  },
  "2026/02/25": {
    "price": 40,
    "open": 39.45,
    "high": 40.05,
    "low": 39.1,
    "volume": 863,
    "sma5": 39.72,
    "sma20": 39.14,
    "sma60": 38.55,
    "sma120": 39.78,
    "sma240": 41.6
  },
  "2026/02/24": {
    "price": 39.45,
    "open": 39.45,
    "high": 39.8,
    "low": 39.3,
    "volume": 847,
    "sma5": 39.64,
    "sma20": 39.1,
    "sma60": 38.49,
    "sma120": 39.81,
    "sma240": 41.65
  },
  "2026/02/23": {
    "price": 39.55,
    "open": 40.35,
    "high": 40.35,
    "low": 39,
    "volume": 879,
    "sma5": 39.46,
    "sma20": 39.08,
    "sma60": 38.43,
    "sma120": 39.85,
    "sma240": 41.71
  },
  "2026/02/11": {
    "price": 40,
    "open": 39.8,
    "high": 40.25,
    "low": 39.65,
    "volume": 940,
    "sma5": 39.36,
    "sma20": 39.07,
    "sma60": 38.38,
    "sma120": 39.89,
    "sma240": 41.76
  },
  "2026/02/10": {
    "price": 39.6,
    "open": 39.6,
    "high": 39.6,
    "low": 39.2,
    "volume": 393,
    "sma5": 39.3,
    "sma20": 39,
    "sma60": 38.33,
    "sma120": 39.93,
    "sma240": 41.81
  },
  "2026/02/09": {
    "price": 39.6,
    "open": 39.1,
    "high": 39.75,
    "low": 38.9,
    "volume": 830,
    "sma5": 39.15,
    "sma20": 38.96,
    "sma60": 38.3,
    "sma120": 39.97,
    "sma240": 41.87
  },
  "2026/02/06": {
    "price": 38.55,
    "open": 39.1,
    "high": 39.1,
    "low": 37.9,
    "volume": 782,
    "sma5": 39.01,
    "sma20": 38.95,
    "sma60": 38.27,
    "sma120": 40.01,
    "sma240": 41.91
  },
  "2026/02/05": {
    "price": 39.05,
    "open": 39.7,
    "high": 39.7,
    "low": 38.95,
    "volume": 611,
    "sma5": 39.2,
    "sma20": 38.95,
    "sma60": 38.26,
    "sma120": 40.05,
    "sma240": 41.97
  },
  "2026/02/04": {
    "price": 39.7,
    "open": 39,
    "high": 40,
    "low": 38.75,
    "volume": 687,
    "sma5": 39.34,
    "sma20": 38.92,
    "sma60": 38.24,
    "sma120": 40.08,
    "sma240": 42.02
  },
  "2026/02/03": {
    "price": 38.85,
    "open": 39.4,
    "high": 39.5,
    "low": 38.25,
    "volume": 1088,
    "sma5": 39.21,
    "sma20": 38.95,
    "sma60": 38.22,
    "sma120": 40.11,
    "sma240": 42.07
  },
  "2026/02/02": {
    "sma5": 39.16,
    "sma20": 38.89,
    "sma60": 38.23,
    "sma120": 40.13,
    "sma240": 42.13
  },
  "2026/01/30": {
    "sma5": 39.24,
    "sma20": 38.85,
    "sma60": 38.23,
    "sma120": 40.17,
    "sma240": 42.19
  },
  "2026/01/29": {
    "sma5": 39.08,
    "sma20": 38.76,
    "sma60": 38.21,
    "sma120": 40.19,
    "sma240": 42.23
  },
  "2026/01/28": {
    "sma5": 38.72,
    "sma20": 38.67,
    "sma60": 38.2,
    "sma120": 40.21,
    "sma240": 42.26
  },
  "2026/01/27": {
    "sma5": 38.51,
    "sma20": 38.61,
    "sma60": 38.2,
    "sma120": 40.22,
    "sma240": 42.29
  },
  "2026/01/26": {
    "sma5": 38.51,
    "sma20": 38.61,
    "sma60": 38.22,
    "sma120": 40.24,
    "sma240": 42.34
  },
  "2026/01/23": {
    "sma5": 38.52,
    "sma20": 38.52,
    "sma60": 38.23,
    "sma120": 40.24,
    "sma240": 42.36
  },
  "2026/01/22": {
    "sma5": 38.56,
    "sma20": 38.47,
    "sma60": 38.25,
    "sma120": 40.26,
    "sma240": 42.39
  },
  "2026/01/21": {
    "sma5": 38.86,
    "sma20": 38.45,
    "sma60": 38.29,
    "sma120": 40.29,
    "sma240": 42.43
  },
  "2026/01/20": {
    "sma5": 38.98,
    "sma20": 38.45,
    "sma60": 38.33,
    "sma120": 40.31,
    "sma240": 42.46
  },
  "2026/01/19": {
    "sma5": 39.03,
    "sma20": 38.39,
    "sma60": 38.37,
    "sma120": 40.34,
    "sma240": 42.5
  },
  "2026/01/16": {
    "sma5": 39.01,
    "sma20": 38.29,
    "sma60": 38.39,
    "sma120": 40.36,
    "sma240": 42.53
  },
  "2026/01/15": {
    "sma5": 38.94,
    "sma20": 38.22,
    "sma60": 38.41,
    "sma120": 40.38,
    "sma240": 42.56
  },
  "2026/01/14": {
    "sma5": 38.75,
    "sma20": 38.13,
    "sma60": 38.44,
    "sma120": 40.39,
    "sma240": 42.59
  },
  "2026/01/13": {
    "sma5": 39.11,
    "sma20": 38.09,
    "sma60": 38.47,
    "sma120": 40.4,
    "sma240": 42.63
  },
  "2026/01/12": {
    "sma5": 38.86,
    "sma20": 38.03,
    "sma60": 38.5,
    "sma120": 40.41,
    "sma240": 42.65
  },
  "2026/01/09": {
    "sma5": 38.64,
    "sma20": 37.94,
    "sma60": 38.52,
    "sma120": 40.42,
    "sma240": 42.68
  },
  "2026/01/08": {
    "sma5": 38.45,
    "sma20": 37.89,
    "sma60": 38.55,
    "sma120": 40.44,
    "sma240": 42.71
  },
  "2026/01/07": {
    "sma5": 38.35,
    "sma20": 37.86,
    "sma60": 38.57,
    "sma120": 40.45,
    "sma240": 42.73
  },
  "2026/01/06": {
    "sma5": 37.85,
    "sma20": 37.75,
    "sma60": 38.57,
    "sma120": 40.44,
    "sma240": 42.75
  },
  "2026/01/05": {
    "sma5": 38.02,
    "sma20": 37.81,
    "sma60": 38.62,
    "sma120": 40.45,
    "sma240": 42.78
  },
  "2026/01/02": {
    "sma5": 37.92,
    "sma20": 37.86,
    "sma60": 38.67,
    "sma120": 40.45,
    "sma240": 42.81
  },
  "2025/12/31": {
    "sma5": 37.91,
    "sma20": 37.91,
    "sma60": 38.73,
    "sma120": 40.45,
    "sma240": 42.84
  },
  "2025/12/30": {
    "sma5": 37.84,
    "sma20": 37.95,
    "sma60": 38.79,
    "sma120": 40.45,
    "sma240": 42.87
  },
  "2025/12/29": {
    "sma5": 37.86,
    "sma20": 38,
    "sma60": 38.86,
    "sma120": 40.46,
    "sma240": 42.91
  },
  "2025/12/26": {
    "sma5": 37.66,
    "sma20": 38.02,
    "sma60": 38.92,
    "sma120": 40.46,
    "sma240": 42.94
  },
  "2025/12/24": {
    "sma5": 37.6,
    "sma20": 38.09,
    "sma60": 39,
    "sma120": 40.47,
    "sma240": 42.97
  },
  "2025/12/23": {
    "sma5": 37.58,
    "sma20": 38.17,
    "sma60": 39.09,
    "sma120": 40.49,
    "sma240": 43.01
  },
  "2025/12/22": {
    "sma5": 37.57,
    "sma20": 38.19,
    "sma60": 39.17,
    "sma120": 40.51,
    "sma240": 43.05
  },
  "2025/12/19": {
    "sma5": 37.55,
    "sma20": 38.14,
    "sma60": 39.24,
    "sma120": 40.52,
    "sma240": 43.08
  },
  "2025/12/18": {
    "sma5": 37.57,
    "sma20": 38.11,
    "sma60": 39.32,
    "sma120": 40.53,
    "sma240": 43.12
  },
  "2025/12/17": {
    "sma5": 37.59,
    "sma20": 38.06,
    "sma60": 39.41,
    "sma120": 40.56,
    "sma240": 43.15
  },
  "2025/12/16": {
    "sma5": 37.61,
    "sma20": 37.99,
    "sma60": 39.5,
    "sma120": 40.58,
    "sma240": 43.18
  },
  "2025/12/15": {
    "sma5": 37.66,
    "sma20": 37.95,
    "sma60": 39.58,
    "sma120": 40.6,
    "sma240": 43.21
  },
  "2025/12/12": {
    "sma5": 37.73,
    "sma20": 37.9,
    "sma60": 39.65,
    "sma120": 40.61,
    "sma240": 43.24
  },
  "2025/12/11": {
    "sma5": 37.99,
    "sma20": 37.9,
    "sma60": 39.71,
    "sma120": 40.62,
    "sma240": 43.27
  },
  "2025/12/10": {
    "sma5": 38.31,
    "sma20": 37.93,
    "sma60": 39.79,
    "sma120": 40.62,
    "sma240": 43.31
  },
  "2025/12/09": {
    "sma5": 38.54,
    "sma20": 37.96,
    "sma60": 39.85,
    "sma120": 40.63,
    "sma240": 43.34
  },
  "2025/12/08": {
    "sma5": 38.74,
    "sma20": 37.95,
    "sma60": 39.94,
    "sma120": 40.66,
    "sma240": 43.37
  },
  "2025/12/05": {
    "sma5": 38.85,
    "sma20": 37.97,
    "sma60": 40.02,
    "sma120": 40.69,
    "sma240": 43.41
  },
  "2025/12/04": {
    "sma5": 38.86,
    "sma20": 37.98,
    "sma60": 40.1,
    "sma120": 40.71,
    "sma240": 43.45
  },
  "2025/12/03": {
    "sma5": 38.87,
    "sma20": 37.97,
    "sma60": 40.18,
    "sma120": 40.72,
    "sma240": 43.5
  },
  "2025/12/02": {
    "sma5": 38.95,
    "sma20": 37.97,
    "sma60": 40.28,
    "sma120": 40.75,
    "sma240": 43.54
  }
}