{
  "2026/06/08": {
    "price": 250,
    "open": 247,
    "high": 254.5,
    "low": 246,
    "volume": 28335,
    "sma5": 279.2,
    "sma20": 282.08,
    "sma60": 244.94,
    "sma120": 202.32,
    "sma240": 168.19
  },
  "2026/06/05": {
    "price": 281,
    "open": 283,
    "high": 284.5,
    "low": 273,
    "volume": 15071,
    "sma5": 286.7,
    "sma20": 282.8,
    "sma60": 244.63,
    "sma120": 201.48,
    "sma240": 167.67
  },
  "2026/06/04": {
    "price": 282,
    "open": 290,
    "high": 291.5,
    "low": 277.5,
    "volume": 14366,
    "sma5": 288.2,
    "sma20": 280.78,
    "sma60": 243.65,
    "sma120": 200.34,
    "sma240": 167.03
  },
  "2026/06/03": {
    "price": 292.5,
    "open": 296,
    "high": 298.5,
    "low": 288,
    "volume": 15504,
    "sma5": 289.7,
    "sma20": 277.63,
    "sma60": 242.54,
    "sma120": 199.14,
    "sma240": 166.37
  },
  "2026/06/02": {
    "price": 290.5,
    "open": 296.5,
    "high": 301,
    "low": 285,
    "volume": 18459,
    "sma5": 290.4,
    "sma20": 273.7,
    "sma60": 241.26,
    "sma120": 197.89,
    "sma240": 165.68
  },
  "2026/06/01": {
    "price": 287.5,
    "open": 286.5,
    "high": 291.5,
    "low": 281,
    "volume": 8860,
    "sma5": 291,
    "sma20": 269.63,
    "sma60": 239.93,
    "sma120": 196.65,
    "sma240": 165
  },
  "2026/05/29": {
    "price": 288.5,
    "open": 291,
    "high": 292,
    "low": 286.5,
    "volume": 7821,
    "sma5": 293.8,
    "sma20": 265.78,
    "sma60": 238.4,
    "sma120": 195.43,
    "sma240": 164.33
  },
  "2026/05/28": {
    "price": 289.5,
    "open": 299.5,
    "high": 299.5,
    "low": 289,
    "volume": 6315,
    "sma5": 293.9,
    "sma20": 261.55,
    "sma60": 236.56,
    "sma120": 194.14,
    "sma240": 163.65
  },
  "2026/05/27": {
    "price": 296,
    "open": 300,
    "high": 304.5,
    "low": 292.5,
    "volume": 9275,
    "sma5": 294.3,
    "sma20": 257.23,
    "sma60": 234.82,
    "sma120": 192.83,
    "sma240": 162.96
  },
  "2026/05/26": {
    "price": 293.5,
    "open": 299,
    "high": 303.5,
    "low": 291.5,
    "volume": 8574,
    "sma5": 290.9,
    "sma20": 252.78,
    "sma60": 232.95,
    "sma120": 191.45,
    "sma240": 162.24
  },
  "2026/05/25": {
    "price": 301.5,
    "open": 292,
    "high": 308,
    "low": 289,
    "volume": 13776,
    "sma5": 285.2,
    "sma20": 248.15,
    "sma60": 231.11,
    "sma120": 190.12,
    "sma240": 161.54
  },
  "2026/05/22": {
    "price": 289,
    "open": 291,
    "high": 301.5,
    "low": 288.5,
    "volume": 12509,
    "sma5": 277.6,
    "sma20": 243.03,
    "sma60": 229.09,
    "sma120": 188.7,
    "sma240": 160.79
  },
  "2026/05/21": {
    "price": 291.5,
    "open": 281,
    "high": 293,
    "low": 278.5,
    "volume": 16764,
    "sma5": 273.8,
    "sma20": 238.88,
    "sma60": 227.23,
    "sma120": 187.39,
    "sma240": 160.1
  },
  "2026/05/20": {
    "price": 279,
    "open": 270.5,
    "high": 291.5,
    "low": 267.5,
    "volume": 23526,
    "sma5": 269.8,
    "sma20": 234.98,
    "sma60": 225.29,
    "sma120": 186.15,
    "sma240": 159.39
  },
  "2026/05/19": {
    "price": 265,
    "open": 265,
    "high": 274.5,
    "low": 262,
    "volume": 9225,
    "sma5": 270.8,
    "sma20": 231.9,
    "sma60": 223.45,
    "sma120": 185.05,
    "sma240": 158.73
  },
  "2026/05/18": {
    "price": 263.5,
    "open": 271,
    "high": 271,
    "low": 258.5,
    "volume": 8559,
    "sma5": 272.9,
    "sma20": 229.5,
    "sma60": 221.63,
    "sma120": 184.09,
    "sma240": 158.13
  },
  "2026/05/15": {
    "price": 270,
    "open": 273,
    "high": 278,
    "low": 267,
    "volume": 15103,
    "sma5": 273.1,
    "sma20": 227.83,
    "sma60": 219.82,
    "sma120": 183.1,
    "sma240": 157.55
  },
  "2026/05/14": {
    "price": 271.5,
    "open": 288,
    "high": 288,
    "low": 270,
    "volume": 16746,
    "sma5": 267.2,
    "sma20": 226.08,
    "sma60": 217.91,
    "sma120": 182.08,
    "sma240": 156.93
  },
  "2026/05/13": {
    "price": 284,
    "open": 272.5,
    "high": 291.5,
    "low": 260,
    "volume": 27420,
    "sma5": 256.7,
    "sma20": 223.98,
    "sma60": 216.04,
    "sma120": 181.04,
    "sma240": 156.31
  },
  "2026/05/12": {
    "price": 275.5,
    "open": 270,
    "high": 283,
    "low": 260,
    "volume": 43177,
    "sma5": 242.7,
    "sma20": 221.15,
    "sma60": 213.92,
    "sma120": 179.92,
    "sma240": 155.63
  },
  "2026/05/11": {
    "price": 264.5,
    "open": 264.5,
    "high": 264.5,
    "low": 248,
    "volume": 22384,
    "sma5": 229.4,
    "sma20": 218.78,
    "sma60": 211.87,
    "sma120": 178.91,
    "sma240": 154.99
  },
  "2026/05/08": {
    "price": 240.5,
    "open": 240.5,
    "high": 240.5,
    "low": 240.5,
    "volume": 6029,
    "sma5": 218.6,
    "sma20": 216.83,
    "sma60": 210.06,
    "sma120": 178.02,
    "sma240": 154.39
  },
  "2026/05/07": {
    "price": 219,
    "open": 219,
    "high": 226,
    "low": 214,
    "volume": 19017,
    "sma5": 211.3,
    "sma20": 216,
    "sma60": 208.7,
    "sma120": 177.26,
    "sma240": 153.88
  },
  "2026/05/06": {
    "price": 214,
    "open": 214.5,
    "high": 219,
    "low": 211.5,
    "volume": 13522,
    "sma5": 208.1,
    "sma20": 216.73,
    "sma60": 207.8,
    "sma120": 176.65,
    "sma240": 153.47
  },
  "2026/05/05": {
    "price": 209,
    "open": 209.5,
    "high": 212,
    "low": 208,
    "volume": 6083,
    "sma5": 206.7,
    "sma20": 217.4,
    "sma60": 206.86,
    "sma120": 176.06,
    "sma240": 153.06
  },
  "2026/05/04": {
    "price": 210.5,
    "open": 206,
    "high": 213.5,
    "low": 206,
    "volume": 10172,
    "sma5": 205.1,
    "sma20": 218.15,
    "sma60": 205.83,
    "sma120": 175.53,
    "sma240": 152.68
  },
  "2026/04/30": {
    "price": 204,
    "open": 203,
    "high": 207.5,
    "low": 202.5,
    "volume": 4991,
    "sma5": 202.8,
    "sma20": 218.88,
    "sma60": 204.77,
    "sma120": 174.95,
    "sma240": 152.29
  },
  "2026/04/29": {
    "price": 203,
    "open": 206.5,
    "high": 207.5,
    "low": 199,
    "volume": 5796,
    "sma5": 203.2,
    "sma20": 219.53,
    "sma60": 203.84,
    "sma120": 174.43,
    "sma240": 151.92
  },
  "2026/04/28": {
    "price": 207,
    "open": 203.5,
    "high": 211,
    "low": 201.5,
    "volume": 7485,
    "sma5": 205.3,
    "sma20": 220.63,
    "sma60": 202.98,
    "sma120": 173.9,
    "sma240": 151.55
  },
  "2026/04/27": {
    "price": 201,
    "open": 200,
    "high": 204,
    "low": 199,
    "volume": 5446,
    "sma5": 207.4,
    "sma20": 221.73,
    "sma60": 201.98,
    "sma120": 173.32,
    "sma240": 151.17
  },
  "2026/04/24": {
    "price": 199,
    "open": 207,
    "high": 208.5,
    "low": 197,
    "volume": 10766,
    "sma5": 210.6,
    "sma20": 223.03,
    "sma60": 201.1,
    "sma120": 172.78,
    "sma240": 150.82
  },
  "2026/04/23": {
    "price": 206,
    "open": 216,
    "high": 217.5,
    "low": 205,
    "volume": 9935,
    "sma5": 216.8,
    "sma20": 224.95,
    "sma60": 200.27,
    "sma120": 172.22,
    "sma240": 150.47
  },
  "2026/04/22": {
    "price": 213.5,
    "open": 215,
    "high": 215,
    "low": 210,
    "volume": 10024,
    "sma5": 222.6,
    "sma20": 226.25,
    "sma60": 199.37,
    "sma120": 171.62,
    "sma240": 150.09
  },
  "2026/04/21": {
    "price": 217.5,
    "open": 219.5,
    "high": 220,
    "low": 213,
    "volume": 8592,
    "sma5": 225.8,
    "sma20": 227.63,
    "sma60": 198.38,
    "sma120": 170.94,
    "sma240": 149.66
  },
  "2026/04/20": {
    "price": 217,
    "open": 227.5,
    "high": 228.5,
    "low": 214,
    "volume": 12831,
    "sma5": 227.8,
    "sma20": 229.45,
    "sma60": 197.28,
    "sma120": 170.27,
    "sma240": 149.18
  },
  "2026/04/17": {
    "price": 230,
    "open": 235.5,
    "high": 235.5,
    "low": 225,
    "volume": 6989,
    "sma5": 230,
    "sma20": 231.1,
    "sma60": 196.07,
    "sma120": 169.63,
    "sma240": 148.71
  },
  "2026/04/16": {
    "price": 235,
    "open": 231.5,
    "high": 236,
    "low": 229.5,
    "volume": 6489,
    "sma5": 229.1,
    "sma20": 232.4,
    "sma60": 194.68,
    "sma120": 168.88,
    "sma240": 148.18
  },
  "2026/04/15": {
    "price": 229.5,
    "open": 231.5,
    "high": 233.5,
    "low": 228,
    "volume": 6764,
    "sma5": 226.9,
    "sma20": 233.13,
    "sma60": 193.18,
    "sma120": 168.08,
    "sma240": 147.61
  },
  "2026/04/14": {
    "price": 227.5,
    "open": 230,
    "high": 238,
    "low": 227,
    "volume": 8193,
    "sma5": 227.7,
    "sma20": 233.4,
    "sma60": 191.82,
    "sma120": 167.32,
    "sma240": 147.08
  },
  "2026/04/13": {
    "price": 228,
    "open": 223.5,
    "high": 229.5,
    "low": 223.5,
    "volume": 4824,
    "sma5": 227.7,
    "sma20": 233.8,
    "sma60": 190.47,
    "sma120": 166.58,
    "sma240": 146.55
  },
  "2026/04/10": {
    "price": 225.5,
    "open": 232.5,
    "high": 234,
    "low": 224.5,
    "volume": 6570,
    "sma5": 226.9,
    "sma20": 233.98,
    "sma60": 188.99,
    "sma120": 165.82,
    "sma240": 146.02
  },
  "2026/04/09": {
    "price": 224,
    "open": 236.5,
    "high": 236.5,
    "low": 223,
    "volume": 5120,
    "sma5": 226.8,
    "sma20": 234.28,
    "sma60": 187.58,
    "sma120": 165.05,
    "sma240": 145.48
  },
  "2026/04/08": {
    "price": 233.5,
    "open": 234.5,
    "high": 234.5,
    "low": 228.5,
    "volume": 3646,
    "sma5": 225.4,
    "sma20": 234.18,
    "sma60": 186.13,
    "sma120": 164.35,
    "sma240": 144.94
  },
  "2026/04/07": {
    "price": 227.5,
    "open": 228,
    "high": 233.5,
    "low": 224,
    "volume": 5678,
    "sma5": 223.7,
    "sma20": 233.28,
    "sma60": 184.52,
    "sma120": 163.6,
    "sma240": 144.33
  },
  "2026/04/02": {
    "price": 224,
    "open": 227.5,
    "high": 230,
    "low": 220.5,
    "volume": 7788,
    "sma5": 224,
    "sma20": 232.68,
    "sma60": 182.99,
    "sma120": 162.87,
    "sma240": 143.76
  },
  "2026/04/01": {
    "price": 225,
    "open": 227,
    "high": 229.5,
    "low": 220.5,
    "volume": 10338,
    "sma5": 224.6,
    "sma20": 232.03,
    "sma60": 181.59,
    "sma120": 162.15,
    "sma240": 143.16
  },
  "2026/03/31": {
    "price": 217,
    "open": 223,
    "high": 224.5,
    "low": 213.5,
    "volume": 10395,
    "sma5": 227.1,
    "sma20": 230.55,
    "sma60": 180.22,
    "sma120": 161.43,
    "sma240": 142.56
  },
  "2026/03/30": {
    "price": 225,
    "open": 222.5,
    "high": 230,
    "low": 220,
    "volume": 6343,
    "sma5": 230.1,
    "sma20": 228.6,
    "sma60": 179.03,
    "sma120": 160.78,
    "sma240": 142.03
  },
  "2026/03/27": {
    "price": 229,
    "open": 224,
    "high": 229,
    "low": 220.5,
    "volume": 8757,
    "sma5": 233.3,
    "sma20": 226.6,
    "sma60": 177.8,
    "sma120": 160.05,
    "sma240": 141.51
  },
  "2026/03/26": {
    "price": 227,
    "open": 236,
    "high": 237,
    "low": 226,
    "volume": 9342,
    "sma5": 238.3,
    "sma20": 224.35,
    "sma60": 176.52,
    "sma120": 159.26,
    "sma240": 140.97
  },
  "2026/03/25": {
    "price": 237.5,
    "open": 238,
    "high": 243,
    "low": 236,
    "volume": 7056,
    "sma5": 242.9,
    "sma20": 222.15,
    "sma60": 175.18,
    "sma120": 158.53,
    "sma240": 140.43
  },
  "2026/03/24": {
    "price": 232,
    "open": 244,
    "high": 245,
    "low": 230.5,
    "volume": 15132,
    "sma5": 246.6,
    "sma20": 219.3,
    "sma60": 173.66,
    "sma120": 157.66,
    "sma240": 139.88
  },
  "2026/03/23": {
    "price": 241,
    "open": 246.5,
    "high": 248,
    "low": 236,
    "volume": 12935,
    "sma5": 250.1,
    "sma20": 216.58,
    "sma60": 172.23,
    "sma120": 156.78,
    "sma240": 139.35
  },
  "2026/03/20": {
    "price": 254,
    "open": 251,
    "high": 256.5,
    "low": 247,
    "volume": 18475,
    "sma5": 248.9,
    "sma20": 213.28,
    "sma60": 170.68,
    "sma120": 155.84,
    "sma240": 138.79
  },
  "2026/03/19": {
    "price": 250,
    "open": 250.5,
    "high": 257,
    "low": 247.5,
    "volume": 9387,
    "sma5": 245.2,
    "sma20": 209,
    "sma60": 168.97,
    "sma120": 154.79,
    "sma240": 138.16
  },
  "2026/03/18": {
    "price": 256,
    "open": 251.5,
    "high": 256,
    "low": 246,
    "volume": 9547,
    "sma5": 241.5,
    "sma20": 204.3,
    "sma60": 167.31,
    "sma120": 153.78,
    "sma240": 137.56
  },
  "2026/03/17": {
    "price": 249.5,
    "open": 237,
    "high": 250,
    "low": 235,
    "volume": 12443,
    "sma5": 236.6,
    "sma20": 199.23,
    "sma60": 165.55,
    "sma120": 152.71,
    "sma240": 136.94
  },
  "2026/03/16": {
    "price": 235,
    "open": 238,
    "high": 243.5,
    "low": 234,
    "volume": 8695,
    "sma5": 231.1,
    "sma20": 194.53,
    "sma60": 163.91,
    "sma120": 151.71,
    "sma240": 136.34
  },
  "2026/03/13": {
    "price": 235.5,
    "open": 230.5,
    "high": 237.5,
    "low": 227,
    "volume": 9068,
    "sma5": 227.2,
    "sma20": 190.75,
    "sma60": 162.53,
    "sma120": 150.82,
    "sma240": 135.81
  },
  "2026/03/12": {
    "price": 231.5,
    "open": 233,
    "high": 236,
    "low": 226,
    "volume": 10904,
    "sma5": 223.2,
    "sma20": 186.8,
    "sma60": 161.08,
    "sma120": 149.93,
    "sma240": 135.28
  },
  "2026/03/11": {
    "price": 231.5,
    "open": 225,
    "high": 236.5,
    "low": 223.5,
    "volume": 18939,
    "sma5": 219.1,
    "sma20": 182.85,
    "sma60": 159.7,
    "sma120": 149.03,
    "sma240": 134.76
  },
  "2026/03/10": {
    "price": 222,
    "open": 219,
    "high": 225,
    "low": 215,
    "volume": 22007,
    "sma5": 211.9,
    "sma20": 179.08,
    "sma60": 158.32,
    "sma120": 148.15,
    "sma240": 134.22
  },
  "2026/03/09": {
    "price": 215.5,
    "open": 200,
    "high": 217,
    "low": 200,
    "volume": 14931,
    "sma5": 203.1,
    "sma20": 175.93,
    "sma60": 157.03,
    "sma120": 147.33,
    "sma240": 133.73
  },
  "2026/03/06": {
    "price": 215.5,
    "open": 208,
    "high": 215.5,
    "low": 204,
    "volume": 12493,
    "sma5": 197,
    "sma20": 173.4,
    "sma60": 155.73,
    "sma120": 146.55,
    "sma240": 133.26
  },
  "2026/03/05": {
    "price": 211,
    "open": 201.5,
    "high": 213.5,
    "low": 200.5,
    "volume": 43341,
    "sma5": 190.7,
    "sma20": 170.5,
    "sma60": 154.53,
    "sma120": 145.77,
    "sma240": 132.79
  },
  "2026/03/04": {
    "price": 195.5,
    "open": 190,
    "high": 195.5,
    "low": 183.5,
    "volume": 31072,
    "sma5": 185.1,
    "sma20": 167.33,
    "sma60": 153.38,
    "sma120": 145.04,
    "sma240": 132.35
  },
  "2026/03/03": {
    "price": 178,
    "open": 186,
    "high": 188,
    "low": 176.5,
    "volume": 10641,
    "sma5": 182.1,
    "sma20": 164.88,
    "sma60": 152.45,
    "sma120": 144.43,
    "sma240": 131.97
  },
  "2026/03/02": {
    "price": 185,
    "open": 182.5,
    "high": 190,
    "low": 180.5,
    "volume": 11490,
    "sma5": 182,
    "sma20": 163.4,
    "sma60": 151.72,
    "sma120": 143.98,
    "sma240": 131.68
  },
  "2026/02/26": {
    "price": 184,
    "open": 183,
    "high": 189.5,
    "low": 180,
    "volume": 10467,
    "sma5": 180,
    "sma20": 161.7,
    "sma60": 150.83,
    "sma120": 143.45,
    "sma240": 131.37
  },
  "2026/02/25": {
    "price": 183,
    "open": 182,
    "high": 183.5,
    "low": 177.5,
    "volume": 8528,
    "sma5": 176.9,
    "sma20": 159.85,
    "sma60": 149.94,
    "sma120": 142.94,
    "sma240": 131.05
  },
  "2026/02/24": {
    "price": 180.5,
    "open": 177,
    "high": 181,
    "low": 173,
    "volume": 6834,
    "sma5": 171.5,
    "sma20": 158.13,
    "sma60": 149.13,
    "sma120": 142.44,
    "sma240": 130.74
  },
  "2026/02/23": {
    "price": 177.5,
    "open": 180.5,
    "high": 184,
    "low": 174.5,
    "volume": 12938,
    "sma5": 166.3,
    "sma20": 156.55,
    "sma60": 148.3,
    "sma120": 141.95,
    "sma240": 130.44
  },
  "2026/02/11": {
    "price": 175,
    "open": 170.5,
    "high": 176,
    "low": 167,
    "volume": 14114,
    "sma5": 161.9,
    "sma20": 155.28,
    "sma60": 147.54,
    "sma120": 141.48,
    "sma240": 130.18
  },
  "2026/02/10": {
    "price": 168.5,
    "open": 169,
    "high": 171,
    "low": 164,
    "volume": 15572,
    "sma5": 158.8,
    "sma20": 154.25,
    "sma60": 147.01,
    "sma120": 141.06,
    "sma240": 129.88
  },
  "2026/02/09": {
    "price": 156,
    "open": 157,
    "high": 157.5,
    "low": 154.5,
    "volume": 3438,
    "sma5": 156.4,
    "sma20": 153.4,
    "sma60": 146.65,
    "sma120": 140.72,
    "sma240": 129.62
  },
  "2026/02/06": {
    "price": 154.5,
    "open": 156,
    "high": 156,
    "low": 151.5,
    "volume": 5493,
    "sma5": 155.7,
    "sma20": 152.8,
    "sma60": 146.54,
    "sma120": 140.46,
    "sma240": 129.41
  },
  "2026/02/05": {
    "price": 155.5,
    "open": 158.5,
    "high": 160,
    "low": 154.5,
    "volume": 4166,
    "sma5": 156,
    "sma20": 152.4,
    "sma60": 146.39,
    "sma120": 140.22,
    "sma240": 129.21
  },
  "2026/02/04": {
    "price": 159.5,
    "open": 154,
    "high": 160,
    "low": 152.5,
    "volume": 4850,
    "sma5": 156.7,
    "sma20": 151.9,
    "sma60": 146.25,
    "sma120": 139.97,
    "sma240": 129.01
  },
  "2026/02/03": {
    "price": 156.5,
    "open": 154,
    "high": 159.5,
    "low": 153,
    "volume": 8204,
    "sma5": 157.8,
    "sma20": 151.3,
    "sma60": 146.04,
    "sma120": 139.68,
    "sma240": 128.78
  }
}