{
  "2026/02/03": {
    "sma5": 40.47,
    "sma20": 38.18,
    "sma60": 36.63,
    "sma120": 38.59,
    "sma240": 41.01
  },
  "2026/02/02": {
    "sma5": 40.43,
    "sma20": 38.02,
    "sma60": 36.6,
    "sma120": 38.59,
    "sma240": 41.08
  },
  "2026/01/30": {
    "sma5": 40.44,
    "sma20": 37.8,
    "sma60": 36.59,
    "sma120": 38.59,
    "sma240": 41.14
  },
  "2026/01/29": {
    "sma5": 39.94,
    "sma20": 37.54,
    "sma60": 36.54,
    "sma120": 38.58,
    "sma240": 41.2
  },
  "2026/01/28": {
    "sma5": 39.21,
    "sma20": 37.21,
    "sma60": 36.48,
    "sma120": 38.55,
    "sma240": 41.24
  },
  "2026/01/27": {
    "sma5": 38.48,
    "sma20": 36.87,
    "sma60": 36.42,
    "sma120": 38.52,
    "sma240": 41.29
  },
  "2026/01/26": {
    "sma5": 38.26,
    "sma20": 36.7,
    "sma60": 36.42,
    "sma120": 38.52,
    "sma240": 41.35
  },
  "2026/01/23": {
    "sma5": 38.06,
    "sma20": 36.5,
    "sma60": 36.43,
    "sma120": 38.52,
    "sma240": 41.41
  },
  "2026/01/22": {
    "sma5": 37.9,
    "sma20": 36.38,
    "sma60": 36.46,
    "sma120": 38.53,
    "sma240": 41.48
  },
  "2026/01/21": {
    "sma5": 37.56,
    "sma20": 36.25,
    "sma60": 36.48,
    "sma120": 38.53,
    "sma240": 41.54
  },
  "2026/01/20": {
    "sma5": 37.29,
    "sma20": 36.12,
    "sma60": 36.5,
    "sma120": 38.53,
    "sma240": 41.6
  },
  "2026/01/19": {
    "sma5": 36.95,
    "sma20": 36.02,
    "sma60": 36.54,
    "sma120": 38.55,
    "sma240": 41.66
  },
  "2026/01/16": {
    "sma5": 36.66,
    "sma20": 35.89,
    "sma60": 36.59,
    "sma120": 38.56,
    "sma240": 41.72
  },
  "2026/01/15": {
    "sma5": 36.45,
    "sma20": 35.83,
    "sma60": 36.64,
    "sma120": 38.57,
    "sma240": 41.78
  },
  "2026/01/14": {
    "sma5": 36.51,
    "sma20": 35.82,
    "sma60": 36.69,
    "sma120": 38.6,
    "sma240": 41.85
  },
  "2026/01/13": {
    "sma5": 36.47,
    "sma20": 35.78,
    "sma60": 36.73,
    "sma120": 38.61,
    "sma240": 41.91
  },
  "2026/01/12": {
    "sma5": 36.42,
    "sma20": 35.81,
    "sma60": 36.79,
    "sma120": 38.64,
    "sma240": 41.97
  },
  "2026/01/09": {
    "sma5": 36.04,
    "sma20": 35.8,
    "sma60": 36.82,
    "sma120": 38.67,
    "sma240": 42.03
  },
  "2026/01/08": {
    "sma5": 35.87,
    "sma20": 35.81,
    "sma60": 36.86,
    "sma120": 38.69,
    "sma240": 42.1
  },
  "2026/01/07": {
    "sma5": 35.56,
    "sma20": 35.78,
    "sma60": 36.9,
    "sma120": 38.71,
    "sma240": 42.16
  },
  "2026/01/06": {
    "sma5": 35.25,
    "sma20": 35.75,
    "sma60": 36.95,
    "sma120": 38.72,
    "sma240": 42.22
  },
  "2026/01/05": {
    "sma5": 35.18,
    "sma20": 35.76,
    "sma60": 37.03,
    "sma120": 38.74,
    "sma240": 42.3
  },
  "2026/01/02": {
    "sma5": 35.25,
    "sma20": 35.85,
    "sma60": 37.12,
    "sma120": 38.77,
    "sma240": 42.38
  },
  "2025/12/31": {
    "sma5": 35.28,
    "sma20": 35.87,
    "sma60": 37.21,
    "sma120": 38.79,
    "sma240": 42.46
  },
  "2025/12/30": {
    "sma5": 35.35,
    "sma20": 35.88,
    "sma60": 37.29,
    "sma120": 38.82,
    "sma240": 42.54
  },
  "2025/12/29": {
    "sma5": 35.46,
    "sma20": 35.87,
    "sma60": 37.38,
    "sma120": 38.84,
    "sma240": 42.61
  },
  "2025/12/26": {
    "sma5": 35.51,
    "sma20": 35.91,
    "sma60": 37.47,
    "sma120": 38.87,
    "sma240": 42.69
  },
  "2025/12/24": {
    "sma5": 35.62,
    "sma20": 35.96,
    "sma60": 37.56,
    "sma120": 38.91,
    "sma240": 42.78
  },
  "2025/12/23": {
    "sma5": 35.71,
    "sma20": 35.95,
    "sma60": 37.67,
    "sma120": 38.95,
    "sma240": 42.87
  },
  "2025/12/22": {
    "sma5": 35.84,
    "sma20": 35.93,
    "sma60": 37.78,
    "sma120": 38.99,
    "sma240": 42.96
  },
  "2025/12/19": {
    "sma5": 35.95,
    "sma20": 35.85,
    "sma60": 37.89,
    "sma120": 39.02,
    "sma240": 43.05
  },
  "2025/12/18": {
    "sma5": 36.14,
    "sma20": 35.8,
    "sma60": 38.02,
    "sma120": 39.06,
    "sma240": 43.14
  },
  "2025/12/17": {
    "sma5": 36.29,
    "sma20": 35.78,
    "sma60": 38.16,
    "sma120": 39.11,
    "sma240": 43.23
  },
  "2025/12/16": {
    "sma5": 36.37,
    "sma20": 35.72,
    "sma60": 38.31,
    "sma120": 39.15,
    "sma240": 43.33
  },
  "2025/12/15": {
    "sma5": 36.36,
    "sma20": 35.67,
    "sma60": 38.47,
    "sma120": 39.18,
    "sma240": 43.41
  },
  "2025/12/12": {
    "sma5": 36.33,
    "sma20": 35.69,
    "sma60": 38.62,
    "sma120": 39.23,
    "sma240": 43.5
  },
  "2025/12/11": {
    "sma5": 36.21,
    "sma20": 35.73,
    "sma60": 38.72,
    "sma120": 39.26,
    "sma240": 43.58
  },
  "2025/12/10": {
    "sma5": 36.25,
    "sma20": 35.81,
    "sma60": 38.77,
    "sma120": 39.3,
    "sma240": 43.65
  },
  "2025/12/09": {
    "sma5": 36.11,
    "sma20": 35.88,
    "sma60": 38.81,
    "sma120": 39.35,
    "sma240": 43.71
  },
  "2025/12/08": {
    "sma5": 35.95,
    "sma20": 35.93,
    "sma60": 38.86,
    "sma120": 39.4,
    "sma240": 43.77
  },
  "2025/12/05": {
    "sma5": 35.75,
    "sma20": 35.97,
    "sma60": 38.94,
    "sma120": 39.45,
    "sma240": 43.84
  },
  "2025/12/04": {
    "sma5": 35.77,
    "sma20": 36.04,
    "sma60": 39.03,
    "sma120": 39.51,
    "sma240": 43.91
  },
  "2025/12/03": {
    "sma5": 35.66,
    "sma20": 36.11,
    "sma60": 39.12,
    "sma120": 39.56,
    "sma240": 43.98
  },
  "2025/12/02": {
    "sma5": 35.62,
    "sma20": 36.21,
    "sma60": 39.21,
    "sma120": 39.62,
    "sma240": 44.06
  },
  "2025/12/01": {
    "sma5": 35.55,
    "sma20": 36.34,
    "sma60": 39.31,
    "sma120": 39.68,
    "sma240": 44.13
  },
  "2025/11/28": {
    "sma5": 35.37,
    "sma20": 36.51,
    "sma60": 39.41,
    "sma120": 39.75,
    "sma240": 44.21
  },
  "2025/11/27": {
    "sma5": 35.07,
    "sma20": 36.66,
    "sma60": 39.5,
    "sma120": 39.8,
    "sma240": 44.28
  },
  "2025/11/26": {
    "sma5": 34.91,
    "sma20": 36.82,
    "sma60": 39.61,
    "sma120": 39.86,
    "sma240": 44.34
  },
  "2025/11/25": {
    "sma5": 34.78,
    "sma20": 37.05,
    "sma60": 39.71,
    "sma120": 39.92,
    "sma240": 44.4
  },
  "2025/11/24": {
    "sma5": 34.82,
    "sma20": 37.27,
    "sma60": 39.83,
    "sma120": 39.98,
    "sma240": 44.46
  },
  "2025/11/21": {
    "sma5": 35.29,
    "sma20": 37.54,
    "sma60": 39.94,
    "sma120": 40.03,
    "sma240": 44.53
  },
  "2025/11/20": {
    "sma5": 35.87,
    "sma20": 37.81,
    "sma60": 40.06,
    "sma120": 40.08,
    "sma240": 44.59
  },
  "2025/11/19": {
    "sma5": 36.4,
    "sma20": 38.09,
    "sma60": 40.16,
    "sma120": 40.14,
    "sma240": 44.66
  },
  "2025/11/18": {
    "sma5": 37,
    "sma20": 38.36,
    "sma60": 40.28,
    "sma120": 40.2,
    "sma240": 44.73
  },
  "2025/11/17": {
    "sma5": 37.38,
    "sma20": 38.58,
    "sma60": 40.38,
    "sma120": 40.26,
    "sma240": 44.8
  },
  "2025/11/14": {
    "sma5": 37.45,
    "sma20": 38.73,
    "sma60": 40.43,
    "sma120": 40.32,
    "sma240": 44.86
  },
  "2025/11/13": {
    "sma5": 37.44,
    "sma20": 38.82,
    "sma60": 40.46,
    "sma120": 40.37,
    "sma240": 44.92
  },
  "2025/11/12": {
    "sma5": 37.47,
    "sma20": 38.86,
    "sma60": 40.49,
    "sma120": 40.42,
    "sma240": 44.97
  },
  "2025/11/11": {
    "sma5": 37.45,
    "sma20": 38.9,
    "sma60": 40.51,
    "sma120": 40.46,
    "sma240": 45.02
  },
  "2025/11/10": {
    "sma5": 37.61,
    "sma20": 38.99,
    "sma60": 40.53,
    "sma120": 40.51,
    "sma240": 45.08
  },
  "2025/11/07": {
    "sma5": 37.91,
    "sma20": 39.13,
    "sma60": 40.55,
    "sma120": 40.56,
    "sma240": 45.14
  },
  "2025/11/06": {
    "sma5": 38.27,
    "sma20": 39.28,
    "sma60": 40.57,
    "sma120": 40.61,
    "sma240": 45.2
  },
  "2025/11/05": {
    "sma5": 38.49,
    "sma20": 39.41,
    "sma60": 40.59,
    "sma120": 40.66,
    "sma240": 45.26
  },
  "2025/11/04": {
    "sma5": 38.97,
    "sma20": 39.54,
    "sma60": 40.61,
    "sma120": 40.72,
    "sma240": 45.32
  },
  "2025/11/03": {
    "sma5": 39.28,
    "sma20": 39.66,
    "sma60": 40.63,
    "sma120": 40.76,
    "sma240": 45.39
  }
}